repltable/__init__.py
repltable/db.py
repltable/tables.py
repltable/util.py
repltable-3.0.0.dist-info/WHEEL
repltable-3.0.0.dist-info/METADATA
repltable-3.0.0.dist-info/RECORD
