Metadata-Version: 2.1
Name: repltable
Version: 3.0.0
Summary: a better replit database for python
Home-page: https://github.com/terabyte3/repltable
Keywords: replit,database,table,nosql,db,datastore,repl,repl.it,replit-py
Author: terabyte.
Author-email: terabyte@terabyteis.me
Requires-Python: >=3.8,<4.0
Classifier: Programming Language :: Python :: 3
Classifier: Programming Language :: Python :: 3.10
Classifier: Programming Language :: Python :: 3.8
Classifier: Programming Language :: Python :: 3.9
Classifier: Topic :: Database
Requires-Dist: orjson (>=3.6.8,<4.0.0)
Requires-Dist: urllib3 (>=1.26.9,<2.0.0)
Project-URL: Repository, https://github.com/terabyte3/repltable
